sparkplug_core/__init__.py
sparkplug_core/enums/__init__.py
sparkplug_core/enums/subscription_type.py
sparkplug_core/fields/__init__.py
sparkplug_core/fields/creatable_slug_related_field.py
sparkplug_core/fields/html_field.py
sparkplug_core/mailer.py
sparkplug_core/middleware/__init__.py
sparkplug_core/middleware/camelcase.py
sparkplug_core/middleware/timezone.py
sparkplug_core/models/__init__.py
sparkplug_core/models/base_model.py
sparkplug_core/models/subscriber_mixin.py
sparkplug_core/pagination/__init__.py
sparkplug_core/pagination/default_pagination.py
sparkplug_core/pagination/search_pagination.py
sparkplug_core/pagination/search_paginator.py
sparkplug_core/permissions/__init__.py
sparkplug_core/permissions/action_permission.py
sparkplug_core/permissions/is_admin.py
sparkplug_core/permissions/is_anonymous.py
sparkplug_core/permissions/is_authenticated.py
sparkplug_core/permissions/is_creator.py
sparkplug_core/permissions/is_not_allowed.py
sparkplug_core/permissions/is_user.py
sparkplug_core/redis/__init__.py
sparkplug_core/redis/content_subscription.py
sparkplug_core/search/__init__.py
sparkplug_core/search/analyzers.py
sparkplug_core/search/preserve_order.py
sparkplug_core/search/token_filters.py
sparkplug_core/typing/__init__.py
sparkplug_core/typing/route.py
sparkplug_core/utils/__init__.py
sparkplug_core/utils/build_cache_key.py
sparkplug_core/utils/get_bool.py
sparkplug_core/utils/get_timezones.py
sparkplug_core/utils/send_admin_action.py
sparkplug_core/utils/send_client_action.py
sparkplug_core/utils/socket_send.py
sparkplug_core/views/__init__.py
sparkplug_core/views/action_queryset.py
sparkplug_core/views/action_serializer.py
sparkplug_core/views/create_with_read_response.py
sparkplug_core/views/generic_serializer.py
sparkplug_core/views/queries.py
sparkplug_core/views/search.py
sparkplug_core/views/search_with_parent.py
sparkplug_core/views/update_with_read_response.py
sparkplug_core/views/view.py
sparkplug_core-1.0.0.dist-info/METADATA
sparkplug_core-1.0.0.dist-info/WHEEL
sparkplug_core-1.0.0.dist-info/RECORD
